{
  "$schema": "https://mintlify.com/docs.json",
  "name": "Afnan Altaf Portfolio",
  "theme": "willow",
  "colors": {
    "primary": "#ff9800",
    "light": "#fff8e1",
    "dark": "#111111"
  },
  "navbar": {
    "primary": {
      "type": "github",
      "href": "https://github.com/afnan-altaf/portfolio"
    }
  },
  "footer": {
    "socials": {
      "github": "https://github.com/afnan-altaf/portfolio"
    }
  },
  "navigation": {
    "groups": [
      {
        "group": "Overview",
        "pages": ["introduction"]
      },
      {
        "group": "Profile",
        "pages": ["skills", "work-experience", "education"]
      },
      {
        "group": "Achievements",
        "pages": ["certifications"]
      },
      {
        "group": "Connect",
        "pages": ["contact"]
      }
    ]
  }
}
